agentops/__init__.py
agentops/config.py
agentops/enums.py
agentops/exceptions.py
agentops/validation.py
agentops/client/__init__.py
agentops/client/client.py
agentops/client/api/__init__.py
agentops/client/api/base.py
agentops/client/api/types.py
agentops/client/api/versions/__init__.py
agentops/client/api/versions/v3.py
agentops/client/api/versions/v4.py
agentops/client/http/README.md
agentops/client/http/__init__.py
agentops/client/http/http_adapter.py
agentops/client/http/http_client.py
agentops/helpers/__init__.py
agentops/helpers/dashboard.py
agentops/helpers/deprecation.py
agentops/helpers/env.py
agentops/helpers/serialization.py
agentops/helpers/system.py
agentops/helpers/time.py
agentops/helpers/version.py
agentops/instrumentation/OpenTelemetry.md
agentops/instrumentation/README.md
agentops/instrumentation/__init__.py
agentops/instrumentation/agentic/ag2/__init__.py
agentops/instrumentation/agentic/ag2/instrumentor.py
agentops/instrumentation/agentic/agno/__init__.py
agentops/instrumentation/agentic/agno/instrumentor.py
agentops/instrumentation/agentic/agno/attributes/__init__.py
agentops/instrumentation/agentic/agno/attributes/agent.py
agentops/instrumentation/agentic/agno/attributes/metrics.py
agentops/instrumentation/agentic/agno/attributes/storage.py
agentops/instrumentation/agentic/agno/attributes/team.py
agentops/instrumentation/agentic/agno/attributes/tool.py
agentops/instrumentation/agentic/agno/attributes/workflow.py
agentops/instrumentation/agentic/crewai/LICENSE
agentops/instrumentation/agentic/crewai/NOTICE.md
agentops/instrumentation/agentic/crewai/__init__.py
agentops/instrumentation/agentic/crewai/crewai_span_attributes.py
agentops/instrumentation/agentic/crewai/instrumentation.py
agentops/instrumentation/agentic/crewai/version.py
agentops/instrumentation/agentic/google_adk/__init__.py
agentops/instrumentation/agentic/google_adk/instrumentor.py
agentops/instrumentation/agentic/google_adk/patch.py
mseep_agentops-0.4.24.dist-info/METADATA
mseep_agentops-0.4.24.dist-info/WHEEL
mseep_agentops-0.4.24.dist-info/licenses/LICENSE
mseep_agentops-0.4.24.dist-info/RECORD
